toy_driving/__init__.py
toy_driving-0.0.1.dist-info/LICENSE
toy_driving-0.0.1.dist-info/METADATA
toy_driving-0.0.1.dist-info/WHEEL
toy_driving-0.0.1.dist-info/top_level.txt
toy_driving-0.0.1.dist-info/RECORD
